velocityvortex/.DS_Store
velocityvortex/__init__.py
velocityvortex/velocityvortex.py
velocityvortex-0.1.3.dist-info/METADATA
velocityvortex-0.1.3.dist-info/WHEEL
velocityvortex-0.1.3.dist-info/RECORD
