Metadata-Version: 2.1
Name: velocityvortex
Version: 0.1.3
Summary: 
Author: Fan-Hsin Sung
Author-email: 147816340+ElephesSung@users.noreply.github.com
Requires-Python: >=3.8,<4.0
Classifier: Programming Language :: Python :: 3
Classifier: Programming Language :: Python :: 3.8
Classifier: Programming Language :: Python :: 3.9
Classifier: Programming Language :: Python :: 3.10
Classifier: Programming Language :: Python :: 3.11
Classifier: Programming Language :: Python :: 3.12
Requires-Dist: numpy (>=1.26.0)
